{
  "timestamp": "2026-02-12T09:40:19.646619-05:00",
  "scan_time": "2026-02-12 09:40:19 ET",
  "buys": [],
  "shorts": [],
  "sells": [],
  "covers": [],
  "holds": [
    {
      "ticker": "GOOGL",
      "price": 310.8599853515625,
      "zone": "FLAT"
    },
    {
      "ticker": "AMZN",
      "price": 203.00999450683594,
      "zone": "SHORT"
    },
    {
      "ticker": "NVDA",
      "price": 192.22000122070312,
      "zone": "LONG"
    },
    {
      "ticker": "ADBE",
      "price": 260.70001220703125,
      "zone": "LONG"
    },
    {
      "ticker": "MA",
      "price": 541.6900024414062,
      "zone": "LONG"
    },
    {
      "ticker": "TMO",
      "price": 516.780029296875,
      "zone": "SHORT"
    },
    {
      "ticker": "MMM",
      "price": 174.83999633789062,
      "zone": "LONG"
    },
    {
      "ticker": "UNP",
      "price": 264.6549987792969,
      "zone": "LONG"
    },
    {
      "ticker": "CRM",
      "price": 187.65499877929688,
      "zone": "LONG"
    },
    {
      "ticker": "INTU",
      "price": 404.17999267578125,
      "zone": "FLAT"
    },
    {
      "ticker": "PLD",
      "price": 141.63499450683594,
      "zone": "LONG"
    },
    {
      "ticker": "SPGI",
      "price": 393.5199890136719,
      "zone": "FLAT"
    }
  ],
  "stats": {
    "total_trades": 92,
    "winning_trades": 33,
    "losing_trades": 57,
    "breakeven_trades": 2,
    "win_rate": 35.869565217391305,
    "total_pnl": -66.0408821105957,
    "avg_pnl": -0.7178356751151707,
    "avg_pnl_percent": -0.514001012479432,
    "open_positions": 10
  },
  "zone_counts": {
    "LONG": 57,
    "SHORT": 19,
    "FLAT": 21
  }
}